<Properties StartupConfiguration="{2B8356BC-0D4E-485C-847F-5DA50968E8DE}|Default">
  <MonoDevelop.Ide.Workbench ActiveDocument="SocketFTPClient/Form1.cs">
    <Files>
      <File FileName="SocketFTPClient/Form1.cs" Line="2" Column="2" />
      <File FileName="SocketFTPClient/Program.cs" Line="1" Column="1" />
    </Files>
  </MonoDevelop.Ide.Workbench>
  <MonoDevelop.Ide.Workspace ActiveConfiguration="Debug" />
  <MonoDevelop.Ide.DebuggingService.Breakpoints>
    <BreakpointStore />
  </MonoDevelop.Ide.DebuggingService.Breakpoints>
  <MonoDevelop.Ide.DebuggingService.PinnedWatches />
  <MonoDevelop.Ide.ItemProperties.SocketFTPClient PreferredExecutionTarget="MonoDevelop.Default" />
  <MultiItemStartupConfigurations />
</Properties>